jitprofiler/__init__.py
jitprofiler/jitprofiler.py
jitprofiler-0.3.0.dist-info/licenses/LICENSE
jitprofiler-0.3.0.dist-info/METADATA
jitprofiler-0.3.0.dist-info/WHEEL
jitprofiler-0.3.0.dist-info/top_level.txt
jitprofiler-0.3.0.dist-info/RECORD
